INSTALL
MANIFEST.in
setup.cfg
setup.py
test.py
svnmock/__init__.py
svnmock/client.py
svnmock/common.py
svnmock/core.py
svnmock/delta.py
svnmock/fs.py
svnmock/mock.py
svnmock/ra.py
svnmock/repos.py
svnmock/trace.py
svnmock/wc.py
svnmock.egg-info/PKG-INFO
svnmock.egg-info/top_level.txt
svnmock.egg-info/zip-safe
