Metadata-Version: 1.0
Name: svnmock
Version: 0.3
Summary: Testing library for Subversion's python bindings
Home-page: http://oakwinter.com/code/svnmock
Author: Collin Winter
Author-email: collinw@gmail.com
License: MIT License
Keywords: subversion svn testing mock
Platform: UNKNOWN
Classifier: Intended Audience :: Developers
Classifier: License :: OSI Approved :: MIT License
Classifier: Natural Language :: English
Classifier: Operating System :: OS Independent
Classifier: Programming Language :: Python
Classifier: Topic :: Software Development :: Libraries :: Python Modules
